format_byte/__init__.py
format_byte/format_byte.py
format_byte-1.1.1.dist-info/LICENSE
format_byte-1.1.1.dist-info/METADATA
format_byte-1.1.1.dist-info/WHEEL
format_byte-1.1.1.dist-info/top_level.txt
format_byte-1.1.1.dist-info/RECORD
