Metadata-Version: 2.1
Name: format-byte
Version: 1.1.1
Summary: Make a number of bytes readable for humans.
Home-page: https://github.com/ChsHub/format_byte
Author: ChsHub
Author-email: christian1193@web.com
License: MIT License
Platform: UNKNOWN
Classifier: Programming Language :: Python :: 3
